{"v":"5.5.7","fr":60,"ip":0,"op":106,"w":144,"h":144,"nm":"transicion-micro-2","ddd":0,"assets":[],"layers":[{"ddd":0,"ind":1,"ty":4,"nm":"bottom-left-square","sr":1,"ks":{"o":{"a":0,"k":100,"ix":11},"r":{"a":0,"k":0,"ix":10},"p":{"a":0,"k":[60,67.817,0],"ix":2},"a":{"a":0,"k":[250,282.57,0],"ix":1},"s":{"a":0,"k":[24,24,100],"ix":6}},"ao":0,"shapes":[{"ty":"gr","it":[{"ind":0,"ty":"sh","ix":1,"ks":{"a":0,"k":{"i":[[0,0],[0,0],[0,0]],"o":[[0,0],[0,0],[0,0]],"v":[[27.06,27.06],[-27.06,27.06],[-27.06,-27.06]],"c":false},"ix":2},"nm":"Path 1","mn":"ADBE Vector Shape - Group","hd":false},{"ty":"st","c":{"a":0,"k":[0.176000004189,0.8,0.804000016755,1],"ix":3},"o":{"a":0,"k":100,"ix":4},"w":{"a":0,"k":10,"ix":5},"lc":2,"lj":2,"bm":0,"nm":"Stroke 1","mn":"ADBE Vector Graphic - Stroke","hd":false},{"ty":"tr","p":{"a":0,"k":[250,282.57],"ix":2},"a":{"a":0,"k":[0,0],"ix":1},"s":{"a":0,"k":[100,100],"ix":3},"r":{"a":0,"k":0,"ix":6},"o":{"a":0,"k":100,"ix":7},"sk":{"a":0,"k":0,"ix":4},"sa":{"a":0,"k":0,"ix":5},"nm":"Transform"}],"nm":"Group 1","np":2,"cix":2,"bm":0,"ix":1,"mn":"ADBE Vector Group","hd":false},{"ty":"tm","s":{"a":1,"k":[{"i":{"x":[0.389],"y":[1]},"o":{"x":[0.167],"y":[0]},"t":66,"s":[100],"e":[0]},{"t":84}],"ix":1},"e":{"a":0,"k":100,"ix":2},"o":{"a":0,"k":0,"ix":3},"m":1,"ix":2,"nm":"Trim Paths 1","mn":"ADBE Vector Filter - Trim","hd":false}],"ip":66,"op":108,"st":73,"bm":0},{"ddd":0,"ind":2,"ty":4,"nm":"bottom-rigt-square","sr":1,"ks":{"o":{"a":0,"k":100,"ix":11},"r":{"a":0,"k":0,"ix":10},"p":{"a":0,"k":[83.689,67.817,0],"ix":2},"a":{"a":0,"k":[348.704,282.57,0],"ix":1},"s":{"a":0,"k":[24,24,100],"ix":6}},"ao":0,"shapes":[{"ty":"gr","it":[{"ind":0,"ty":"sh","ix":1,"ks":{"a":0,"k":{"i":[[0,0],[0,0],[0,0]],"o":[[0,0],[0,0],[0,0]],"v":[[27.065,-27.06],[27.065,27.06],[-27.065,27.06]],"c":false},"ix":2},"nm":"Path 1","mn":"ADBE Vector Shape - Group","hd":false},{"ty":"st","c":{"a":0,"k":[0.176000004189,0.8,0.804000016755,1],"ix":3},"o":{"a":0,"k":100,"ix":4},"w":{"a":0,"k":10,"ix":5},"lc":2,"lj":2,"bm":0,"nm":"Stroke 1","mn":"ADBE Vector Graphic - Stroke","hd":false},{"ty":"tr","p":{"a":0,"k":[348.704,282.57],"ix":2},"a":{"a":0,"k":[0,0],"ix":1},"s":{"a":0,"k":[100,100],"ix":3},"r":{"a":0,"k":0,"ix":6},"o":{"a":0,"k":100,"ix":7},"sk":{"a":0,"k":0,"ix":4},"sa":{"a":0,"k":0,"ix":5},"nm":"Transform"}],"nm":"Group 2","np":2,"cix":2,"bm":0,"ix":1,"mn":"ADBE Vector Group","hd":false},{"ty":"tm","s":{"a":0,"k":0,"ix":1},"e":{"a":1,"k":[{"i":{"x":[0.389],"y":[1]},"o":{"x":[0.167],"y":[0]},"t":66,"s":[0],"e":[100]},{"t":84}],"ix":2},"o":{"a":0,"k":0,"ix":3},"m":1,"ix":2,"nm":"Trim Paths 1","mn":"ADBE Vector Filter - Trim","hd":false}],"ip":66,"op":108,"st":73,"bm":0},{"ddd":0,"ind":3,"ty":4,"nm":"top-right-square","sr":1,"ks":{"o":{"a":0,"k":100,"ix":11},"r":{"a":0,"k":0,"ix":10},"p":{"a":0,"k":[83.689,44.128,0],"ix":2},"a":{"a":0,"k":[348.705,183.865,0],"ix":1},"s":{"a":0,"k":[24,24,100],"ix":6}},"ao":0,"shapes":[{"ty":"gr","it":[{"ind":0,"ty":"sh","ix":1,"ks":{"a":0,"k":{"i":[[0,0],[0,0],[0,0]],"o":[[0,0],[0,0],[0,0]],"v":[[-27.065,-27.065],[27.065,-27.065],[27.065,27.065]],"c":false},"ix":2},"nm":"Path 1","mn":"ADBE Vector Shape - Group","hd":false},{"ty":"st","c":{"a":0,"k":[0.176000004189,0.8,0.804000016755,1],"ix":3},"o":{"a":0,"k":100,"ix":4},"w":{"a":0,"k":10,"ix":5},"lc":2,"lj":2,"bm":0,"nm":"Stroke 1","mn":"ADBE Vector Graphic - Stroke","hd":false},{"ty":"tr","p":{"a":0,"k":[348.705,183.865],"ix":2},"a":{"a":0,"k":[0,0],"ix":1},"s":{"a":0,"k":[100,100],"ix":3},"r":{"a":0,"k":0,"ix":6},"o":{"a":0,"k":100,"ix":7},"sk":{"a":0,"k":0,"ix":4},"sa":{"a":0,"k":0,"ix":5},"nm":"Transform"}],"nm":"Group 3","np":2,"cix":2,"bm":0,"ix":1,"mn":"ADBE Vector Group","hd":false},{"ty":"tm","s":{"a":0,"k":0,"ix":1},"e":{"a":1,"k":[{"i":{"x":[0.389],"y":[1]},"o":{"x":[0.333],"y":[0]},"t":66,"s":[0],"e":[100]},{"t":84}],"ix":2},"o":{"a":0,"k":0,"ix":3},"m":1,"ix":2,"nm":"Trim Paths 1","mn":"ADBE Vector Filter - Trim","hd":false}],"ip":66,"op":108,"st":73,"bm":0},{"ddd":0,"ind":4,"ty":4,"nm":"top-left-square","sr":1,"ks":{"o":{"a":0,"k":100,"ix":11},"r":{"a":0,"k":0,"ix":10},"p":{"a":0,"k":[60,44.128,0],"ix":2},"a":{"a":0,"k":[250,183.865,0],"ix":1},"s":{"a":0,"k":[24,24,100],"ix":6}},"ao":0,"shapes":[{"ty":"gr","it":[{"ind":0,"ty":"sh","ix":1,"ks":{"a":0,"k":{"i":[[0,0],[0,0],[0,0]],"o":[[0,0],[0,0],[0,0]],"v":[[-27.06,27.065],[-27.06,-27.065],[27.06,-27.065]],"c":false},"ix":2},"nm":"Path 1","mn":"ADBE Vector Shape - Group","hd":false},{"ty":"st","c":{"a":0,"k":[0.176000004189,0.8,0.804000016755,1],"ix":3},"o":{"a":0,"k":100,"ix":4},"w":{"a":0,"k":10,"ix":5},"lc":2,"lj":2,"bm":0,"nm":"Stroke 1","mn":"ADBE Vector Graphic - Stroke","hd":false},{"ty":"tr","p":{"a":0,"k":[250,183.865],"ix":2},"a":{"a":0,"k":[0,0],"ix":1},"s":{"a":0,"k":[100,100],"ix":3},"r":{"a":0,"k":0,"ix":6},"o":{"a":0,"k":100,"ix":7},"sk":{"a":0,"k":0,"ix":4},"sa":{"a":0,"k":0,"ix":5},"nm":"Transform"}],"nm":"Group 4","np":2,"cix":2,"bm":0,"ix":1,"mn":"ADBE Vector Group","hd":false},{"ty":"tm","s":{"a":1,"k":[{"i":{"x":[0.389],"y":[1]},"o":{"x":[0.333],"y":[0]},"t":66,"s":[100],"e":[0]},{"t":84}],"ix":1},"e":{"a":0,"k":100,"ix":2},"o":{"a":0,"k":0,"ix":3},"m":1,"ix":2,"nm":"Trim Paths 1","mn":"ADBE Vector Filter - Trim","hd":false}],"ip":66,"op":108,"st":73,"bm":0},{"ddd":0,"ind":5,"ty":3,"nm":"mono","sr":1,"ks":{"o":{"a":0,"k":0,"ix":11},"r":{"a":0,"k":0,"ix":10},"p":{"a":1,"k":[{"i":{"x":0.7,"y":0.911},"o":{"x":0.368,"y":0},"t":53,"s":[71.75,63.5,0],"e":[71.757,63.059,0],"to":[0.002,0.019,0],"ti":[-0.002,-0.02,0]},{"i":{"x":-0.032,"y":1},"o":{"x":0.755,"y":0.085},"t":56,"s":[71.757,63.059,0],"e":[72.75,72,0],"to":[0.177,1.508,0],"ti":[-0.164,-1.398,0]},{"t":79}],"ix":2},"a":{"a":0,"k":[0,0,0],"ix":1},"s":{"a":1,"k":[{"i":{"x":[0.086,0.086,0.667],"y":[1,1,1]},"o":{"x":[0.653,0.653,0.333],"y":[0,0,0]},"t":53,"s":[55,55,100],"e":[100,100,100]},{"t":81}],"ix":6}},"ao":0,"ip":0,"op":106,"st":-106,"bm":0},{"ddd":0,"ind":6,"ty":4,"nm":"Shape Layer 5","parent":5,"sr":1,"ks":{"o":{"a":1,"k":[{"i":{"x":[0.667],"y":[1]},"o":{"x":[0.333],"y":[0]},"t":50,"s":[100],"e":[0]},{"t":61}],"ix":11},"r":{"a":0,"k":0,"ix":10},"p":{"a":0,"k":[0.467,21.513,0],"ix":2},"a":{"a":0,"k":[0,0,0],"ix":1},"s":{"a":0,"k":[186.916,186.916,100],"ix":6}},"ao":0,"shapes":[{"ty":"gr","it":[{"ind":0,"ty":"sh","ix":1,"ks":{"a":0,"k":{"i":[[0,0],[-6.37,0.21],[18.481,-8.317],[0,0]],"o":[[0,0],[39.015,-1.285],[-24.593,11.068],[0,0]],"v":[[-22.707,-35.579],[21.774,-36.002],[46.23,-5.068],[-13.75,5.5]],"c":false},"ix":2},"nm":"Path 1","mn":"ADBE Vector Shape - Group","hd":false},{"ty":"tm","s":{"a":1,"k":[{"i":{"x":[0.667],"y":[0.852]},"o":{"x":[0.333],"y":[0]},"t":34,"s":[0],"e":[91.285]},{"i":{"x":[0.667],"y":[1]},"o":{"x":[0.333],"y":[1.707]},"t":44,"s":[91.285],"e":[100]},{"t":55}],"ix":1},"e":{"a":1,"k":[{"i":{"x":[0.667],"y":[1]},"o":{"x":[0.333],"y":[0]},"t":35,"s":[30],"e":[100]},{"t":56}],"ix":2},"o":{"a":0,"k":0,"ix":3},"m":1,"ix":2,"nm":"Trim Paths 1","mn":"ADBE Vector Filter - Trim","hd":false},{"ty":"st","c":{"a":0,"k":[0.078431372549,0.392156862745,0.647058823529,1],"ix":3},"o":{"a":0,"k":100,"ix":4},"w":{"a":1,"k":[{"i":{"x":[0.667],"y":[1]},"o":{"x":[0.333],"y":[0]},"t":39,"s":[5],"e":[2]},{"t":54}],"ix":5},"lc":2,"lj":2,"bm":0,"nm":"Stroke 1","mn":"ADBE Vector Graphic - Stroke","hd":false},{"ty":"tr","p":{"a":0,"k":[0,0],"ix":2},"a":{"a":0,"k":[0,0],"ix":1},"s":{"a":0,"k":[100,100],"ix":3},"r":{"a":0,"k":0,"ix":6},"o":{"a":0,"k":100,"ix":7},"sk":{"a":0,"k":0,"ix":4},"sa":{"a":0,"k":0,"ix":5},"nm":"Transform"}],"nm":"Shape 1","np":4,"cix":2,"bm":0,"ix":1,"mn":"ADBE Vector Group","hd":false}],"ip":34,"op":55,"st":-73,"bm":0},{"ddd":0,"ind":7,"ty":4,"nm":"Shape Layer 4","parent":5,"sr":1,"ks":{"o":{"a":0,"k":100,"ix":11},"r":{"a":0,"k":0,"ix":10},"p":{"a":0,"k":[0.467,18.242,0],"ix":2},"a":{"a":0,"k":[0,0,0],"ix":1},"s":{"a":0,"k":[186.916,186.916,100],"ix":6}},"ao":0,"shapes":[{"ty":"gr","it":[{"ind":0,"ty":"sh","ix":1,"ks":{"a":0,"k":{"i":[[-0.402,1.747],[-28.917,0],[18.693,-8.096],[0,0]],"o":[[2.273,0],[28.917,0],[-30.673,15.25],[0,0]],"v":[[-23.923,-36.843],[27.008,-36.754],[45.5,-4.339],[-13.5,6.75]],"c":false},"ix":2},"nm":"Path 1","mn":"ADBE Vector Shape - Group","hd":false},{"ty":"tm","s":{"a":1,"k":[{"i":{"x":[0.667],"y":[1]},"o":{"x":[0.333],"y":[0]},"t":34,"s":[0],"e":[100]},{"t":57}],"ix":1},"e":{"a":1,"k":[{"i":{"x":[0.667],"y":[1]},"o":{"x":[0.333],"y":[0]},"t":35,"s":[30],"e":[100]},{"t":51}],"ix":2},"o":{"a":0,"k":0,"ix":3},"m":1,"ix":2,"nm":"Trim Paths 1","mn":"ADBE Vector Filter - Trim","hd":false},{"ty":"st","c":{"a":0,"k":[0.286274509804,0.647058823529,0.901960784314,1],"ix":3},"o":{"a":0,"k":100,"ix":4},"w":{"a":1,"k":[{"i":{"x":[0.667],"y":[1]},"o":{"x":[0.333],"y":[0]},"t":44,"s":[7],"e":[3.5]},{"t":49}],"ix":5},"lc":2,"lj":2,"bm":0,"nm":"Stroke 1","mn":"ADBE Vector Graphic - Stroke","hd":false},{"ty":"tr","p":{"a":0,"k":[0,0],"ix":2},"a":{"a":0,"k":[0,0],"ix":1},"s":{"a":0,"k":[100,100],"ix":3},"r":{"a":0,"k":0,"ix":6},"o":{"a":0,"k":100,"ix":7},"sk":{"a":0,"k":0,"ix":4},"sa":{"a":0,"k":0,"ix":5},"nm":"Transform"}],"nm":"Shape 1","np":4,"cix":2,"bm":0,"ix":1,"mn":"ADBE Vector Group","hd":false}],"ip":34,"op":56,"st":-73,"bm":0},{"ddd":0,"ind":8,"ty":4,"nm":"right-arm","parent":5,"sr":1,"ks":{"o":{"a":0,"k":100,"ix":11},"r":{"a":0,"k":0,"ix":10},"p":{"a":0,"k":[6.667,38.882,0],"ix":2},"a":{"a":0,"k":[327.542,462.226,0],"ix":1},"s":{"a":0,"k":[24,24,100],"ix":6}},"ao":0,"shapes":[{"ty":"gr","it":[{"ind":0,"ty":"sh","ix":1,"ks":{"a":1,"k":[{"i":{"x":0.667,"y":1},"o":{"x":0.765,"y":0},"t":42,"s":[{"i":[[-1.972,-0.126],[0,0],[-3.767,-2.735],[4.063,-3.779],[4.313,0.303],[0,0],[1.581,0.824],[0,0],[-0.174,6.201],[-4.245,1.238]],"o":[[1.972,0.126],[1.656,0.638],[6.06,4.144],[-3.307,1.626],[-4.025,-0.283],[-3.534,0.139],[0,0],[-6.083,-1.216],[0.06,-2.17],[0,0]],"v":[[-86.919,-18.922],[-80.215,-12.554],[-73.809,-5.25],[-59.528,0.707],[-64.706,4.581],[-74.042,3.668],[-83.088,1.509],[-91.458,-1.061],[-101.688,-13.901],[-94.95,-19.542]],"c":true}],"e":[{"i":[[0,0],[0,0],[-14.577,-1.261],[-2.325,-3.779],[4.278,-0.632],[0,0],[9.89,1.3],[0,0],[-0.174,6.201],[-0.18,4.42]],"o":[[0,0],[7.552,1.621],[5.569,1.687],[7.839,-0.077],[-11.395,1.682],[-18.274,0.139],[0,0],[-6.083,-1.216],[0.06,-2.17],[0,0]],"v":[[-58.42,-12.534],[-50.734,-10.098],[-26.639,-6.724],[-4.497,-0.767],[-12.132,4.581],[-30.803,6.616],[-77.192,2.001],[-91.458,-1.061],[-101.688,-13.901],[-101.338,-22.981]],"c":true}]},{"i":{"x":0.667,"y":1},"o":{"x":0.333,"y":0},"t":44,"s":[{"i":[[0,0],[0,0],[-14.577,-1.261],[-2.325,-3.779],[4.278,-0.632],[0,0],[9.89,1.3],[0,0],[-0.174,6.201],[-0.18,4.42]],"o":[[0,0],[7.552,1.621],[5.569,1.687],[7.839,-0.077],[-11.395,1.682],[-18.274,0.139],[0,0],[-6.083,-1.216],[0.06,-2.17],[0,0]],"v":[[-58.42,-12.534],[-50.734,-10.098],[-26.639,-6.724],[-4.497,-0.767],[-12.132,4.581],[-30.803,6.616],[-77.192,2.001],[-91.458,-1.061],[-101.688,-13.901],[-101.338,-22.981]],"c":true}],"e":[{"i":[[0,0],[0,0],[-9.695,-0.801],[-7.49,0.82],[-3.457,-1.305],[0,0],[43.079,2.239],[0,0],[-0.174,6.201],[-0.18,4.42]],"o":[[0,0],[5.858,-0.246],[6.029,-1.293],[8.234,1.311],[6.62,6.718],[-0.566,12.643],[0,0],[-6.083,-1.216],[0.06,-2.17],[0,0]],"v":[[-9.301,-13.371],[9.923,-12.161],[29.407,-11.115],[48.33,-12.245],[63.702,-11.755],[67.939,-2.448],[27.242,22.696],[-91.458,-1.061],[-101.688,-13.901],[-101.338,-22.981]],"c":true}]},{"i":{"x":0.667,"y":1},"o":{"x":0.333,"y":0},"t":46,"s":[{"i":[[0,0],[0,0],[-9.695,-0.801],[-7.49,0.82],[-3.457,-1.305],[0,0],[43.079,2.239],[0,0],[-0.174,6.201],[-0.18,4.42]],"o":[[0,0],[5.858,-0.246],[6.029,-1.293],[8.234,1.311],[6.62,6.718],[-0.566,12.643],[0,0],[-6.083,-1.216],[0.06,-2.17],[0,0]],"v":[[-9.301,-13.371],[9.923,-12.161],[29.407,-11.115],[48.33,-12.245],[63.702,-11.755],[67.939,-2.448],[27.242,22.696],[-91.458,-1.061],[-101.688,-13.901],[-101.338,-22.981]],"c":true}],"e":[{"i":[[0,0],[0,0],[0.56,3.51],[-3.455,-0.035],[-7.659,-1.671],[0,0],[9.89,1.3],[0,0],[-0.174,6.201],[-0.18,4.42]],"o":[[0,0],[3.9,-3.42],[3.44,-0.321],[7.839,-0.077],[0,0],[0,9.88],[0,0],[-6.083,-1.216],[0.06,-2.17],[0,0]],"v":[[47.712,-11.551],[60.312,-22.382],[68.192,-34.731],[78.542,-35.161],[101.862,-32.762],[101.862,18.409],[83.972,33.939],[-91.458,-1.061],[-101.688,-13.901],[-101.338,-22.981]],"c":true}]},{"t":55}],"ix":2},"nm":"Path 1","mn":"ADBE Vector Shape - Group","hd":false},{"ty":"fl","c":{"a":0,"k":[0.969000004787,0.698000021542,0.497999991623,1],"ix":4},"o":{"a":0,"k":100,"ix":5},"r":1,"bm":0,"nm":"Fill 1","mn":"ADBE Vector Graphic - Fill","hd":false},{"ty":"tr","p":{"a":0,"k":[327.458,462.762],"ix":2},"a":{"a":0,"k":[0,0],"ix":1},"s":{"a":0,"k":[100,100],"ix":3},"r":{"a":0,"k":0,"ix":6},"o":{"a":0,"k":100,"ix":7},"sk":{"a":0,"k":0,"ix":4},"sa":{"a":0,"k":0,"ix":5},"nm":"Transform"}],"nm":"Group 5","np":2,"cix":2,"bm":0,"ix":1,"mn":"ADBE Vector Group","hd":false}],"ip":42,"op":106,"st":23,"bm":0},{"ddd":0,"ind":9,"ty":4,"nm":"t-shirt-detail","parent":5,"sr":1,"ks":{"o":{"a":1,"k":[{"i":{"x":[0.667],"y":[1]},"o":{"x":[0.333],"y":[0]},"t":50,"s":[0],"e":[100]},{"t":56}],"ix":11},"r":{"a":0,"k":0,"ix":10},"p":{"a":1,"k":[{"i":{"x":0.667,"y":1},"o":{"x":0.333,"y":0},"t":55,"s":[-16.565,28.444,0],"e":[-16.565,30.652,0],"to":[0,0.368,0],"ti":[0,-0.368,0]},{"t":90}],"ix":2},"a":{"a":0,"k":[230.98,428.77,0],"ix":1},"s":{"a":0,"k":[24,24,100],"ix":6}},"ao":0,"shapes":[{"ty":"gr","it":[{"ind":0,"ty":"sh","ix":1,"ks":{"a":0,"k":{"i":[[-5.888,10.38],[-1.51,-13.861],[0,0],[0,0]],"o":[[-3.27,16.399],[0,0],[0,0],[0.765,-11.909]],"v":[[5.21,-22.86],[1.96,22.86],[-5.21,22.86],[-4.9,11.01]],"c":true},"ix":2},"nm":"Path 1","mn":"ADBE Vector Shape - Group","hd":false},{"ty":"fl","c":{"a":0,"k":[0,0.180000005984,0.395999983245,1],"ix":4},"o":{"a":0,"k":100,"ix":5},"r":1,"bm":0,"nm":"Fill 1","mn":"ADBE Vector Graphic - Fill","hd":false},{"ty":"tr","p":{"a":0,"k":[230.98,428.77],"ix":2},"a":{"a":0,"k":[0,0],"ix":1},"s":{"a":0,"k":[100,100],"ix":3},"r":{"a":0,"k":0,"ix":6},"o":{"a":0,"k":100,"ix":7},"sk":{"a":0,"k":0,"ix":4},"sa":{"a":0,"k":0,"ix":5},"nm":"Transform"}],"nm":"Group 6","np":2,"cix":2,"bm":0,"ix":1,"mn":"ADBE Vector Group","hd":false}],"ip":23,"op":106,"st":23,"bm":0},{"ddd":0,"ind":10,"ty":4,"nm":"left-hand2 :M","parent":5,"sr":1,"ks":{"o":{"a":0,"k":100,"ix":11},"r":{"a":0,"k":0,"ix":10},"p":{"a":0,"k":[15.719,31.912,0],"ix":2},"a":{"a":0,"k":[79.949,81.165,0],"ix":1},"s":{"a":0,"k":[184,184,100],"ix":6}},"ao":0,"shapes":[{"ty":"gr","it":[{"ty":"gr","it":[{"ind":0,"ty":"sh","ix":1,"ks":{"a":1,"k":[{"i":{"x":0.667,"y":1},"o":{"x":0.333,"y":0},"t":45,"s":[{"i":[[-2.53,-5.93],[-2,0.87],[-4.17,7.731],[2.231,0.709],[0,0]],"o":[[0.94,2.19],[11.57,-5],[4.49,-6],[-5.15,-1.64],[-20.55,11.78]],"v":[[-18.945,24.224],[-10.945,33.525],[9.114,18.957],[0.283,21.785],[-12.708,23.573]],"c":true}],"e":[{"i":[[-2.53,-5.93],[-2,0.87],[-4.17,7.731],[2.231,0.709],[0,0]],"o":[[0.94,2.19],[11.57,-5],[4.49,-6],[-5.15,-1.64],[-20.55,11.78]],"v":[[-18.945,24.224],[-10.945,33.525],[31.225,-0.206],[22.885,-32.755],[-15.165,5.884]],"c":true}]},{"t":55}],"ix":2},"nm":"Path 1","mn":"ADBE Vector Shape - Group","hd":false},{"ty":"fl","c":{"a":0,"k":[0.882000029087,0.569000005722,0.352999985218,1],"ix":4},"o":{"a":0,"k":100,"ix":5},"r":1,"bm":0,"nm":"Fill 1","mn":"ADBE Vector Graphic - Fill","hd":false},{"ty":"tr","p":{"a":0,"k":[363.325,432.586],"ix":2},"a":{"a":0,"k":[0,0],"ix":1},"s":{"a":0,"k":[100,100],"ix":3},"r":{"a":0,"k":0,"ix":6},"o":{"a":0,"k":100,"ix":7},"sk":{"a":0,"k":0,"ix":4},"sa":{"a":0,"k":0,"ix":5},"nm":"Transform"}],"nm":"Group 7","np":2,"cix":2,"bm":0,"ix":1,"mn":"ADBE Vector Group","hd":false},{"ty":"tr","p":{"a":0,"k":[80.2,81.165],"ix":2},"a":{"a":0,"k":[366.434,432.979],"ix":1},"s":{"a":0,"k":[12.72,12.72],"ix":3},"r":{"a":0,"k":0,"ix":6},"o":{"a":0,"k":100,"ix":7},"sk":{"a":0,"k":0,"ix":4},"sa":{"a":0,"k":0,"ix":5},"nm":"Transform"}],"nm":"left-hand2","np":1,"cix":2,"bm":0,"ix":1,"mn":"ADBE Vector Group","hd":false},{"ty":"gr","it":[{"ty":"gr","it":[{"ind":0,"ty":"sh","ix":1,"ks":{"a":1,"k":[{"i":{"x":0.667,"y":1},"o":{"x":0.333,"y":0},"t":45,"s":[{"i":[[0,0],[0,0],[0,0],[0,0],[0,0],[-0.956,-1.144],[0.743,-1.001],[0,0],[0,0],[0,0],[0,0],[-3.302,-2.878],[-1.491,3.84],[-0.201,0.341]],"o":[[0,0],[0,0],[0,0],[0,0],[1.145,-0.956],[0.8,0.956],[0,0],[0,0],[0,0],[0,0],[-1.493,3.842],[3.302,2.878],[0.149,-0.38],[0,0]],"v":[[-28.175,35.758],[-20.694,33.378],[-20.294,32.708],[-19.984,32.438],[-4.901,24.156],[1.359,29.903],[-0.018,31.767],[-7.548,34.915],[-12.974,39.688],[-11.783,38.118],[-20.51,44.753],[-27.222,44.1],[-38.051,35.069],[-32.916,35.315]],"c":true}],"e":[{"i":[[0,0],[0,0],[0,0],[0,0],[0,0],[-0.956,-1.144],[0.743,-1.001],[0,0],[0,0],[0,0],[0,0],[3.844,1.489],[-1.491,3.84],[-0.201,0.341]],"o":[[0,0],[0,0],[0,0],[0,0],[1.145,-0.956],[0.8,0.956],[0,0],[0,0],[0,0],[0,0],[-1.493,3.842],[-3.84,-1.489],[0.149,-0.38],[0,0]],"v":[[-15.892,14.139],[-1.532,-9.861],[-1.132,-10.531],[-0.822,-10.801],[16.718,-25.961],[20.521,-25.619],[20.618,-22.281],[20.459,-22.082],[6.188,-3.551],[7.379,-5.121],[-2.822,21.169],[-12.482,25.428],[-19.871,20.82],[-16.211,14.678]],"c":true}]},{"t":56}],"ix":2},"nm":"Path 1","mn":"ADBE Vector Shape - Group","hd":false},{"ty":"fl","c":{"a":0,"k":[0.882000029087,0.569000005722,0.352999985218,1],"ix":4},"o":{"a":0,"k":100,"ix":5},"r":1,"bm":0,"nm":"Fill 1","mn":"ADBE Vector Graphic - Fill","hd":false},{"ty":"tr","p":{"a":0,"k":[353.401,426.961],"ix":2},"a":{"a":0,"k":[0,0],"ix":1},"s":{"a":0,"k":[100,100],"ix":3},"r":{"a":0,"k":0,"ix":6},"o":{"a":0,"k":100,"ix":7},"sk":{"a":0,"k":0,"ix":4},"sa":{"a":0,"k":0,"ix":5},"nm":"Transform"}],"nm":"Group 8","np":2,"cix":2,"bm":0,"ix":1,"mn":"ADBE Vector Group","hd":false},{"ty":"tr","p":{"a":0,"k":[78.607,80.358],"ix":2},"a":{"a":0,"k":[353.907,426.634],"ix":1},"s":{"a":0,"k":[12.72,12.72],"ix":3},"r":{"a":0,"k":0,"ix":6},"o":{"a":0,"k":100,"ix":7},"sk":{"a":0,"k":0,"ix":4},"sa":{"a":0,"k":0,"ix":5},"nm":"Transform"}],"nm":"left-hand","np":1,"cix":2,"bm":0,"ix":2,"mn":"ADBE Vector Group","hd":false}],"ip":45,"op":106,"st":-107,"bm":0},{"ddd":0,"ind":11,"ty":4,"nm":"neck-shadow","parent":5,"sr":1,"ks":{"o":{"a":1,"k":[{"i":{"x":[0.667],"y":[1]},"o":{"x":[0.333],"y":[0]},"t":59,"s":[0],"e":[48]},{"t":75}],"ix":11},"r":{"a":0,"k":0,"ix":10},"p":{"a":0,"k":[-7.906,10.272,0],"ix":2},"a":{"a":0,"k":[267.06,344,0],"ix":1},"s":{"a":1,"k":[{"i":{"x":[0.667,0.667,0.667],"y":[1,1,1]},"o":{"x":[0.167,0.167,0.167],"y":[0,0,0]},"t":56,"s":[24,24,100],"e":[24,24,100]},{"t":81}],"ix":6}},"ao":0,"shapes":[{"ty":"gr","it":[{"ind":0,"ty":"sh","ix":1,"ks":{"a":0,"k":{"i":[[-6.3,-4.85],[-1.16,0.96],[-9.57,9.38],[-2.245,4.208],[1.592,-1.014],[6.991,0.66],[4.3,3.58],[2.24,2.861],[0.78,-8.75]],"o":[[1,-0.9],[12.88,-10.82],[3.384,-3.362],[-1.452,1.204],[-5.993,3.659],[-9.21,-1],[-2.787,-2.331],[-0.78,8.75],[0.86,6.32]],"v":[[-15.79,21.98],[-12.63,19.19],[18.54,-1.12],[27.03,-12.54],[22.46,-9.21],[2.46,-4.59],[-17.12,-14.17],[-24.68,-21.98],[-27.03,4.21]],"c":true},"ix":2},"nm":"Path 1","mn":"ADBE Vector Shape - Group","hd":false},{"ty":"fl","c":{"a":0,"k":[0.847000002394,0.447000002394,0.172999991623,1],"ix":4},"o":{"a":0,"k":100,"ix":5},"r":1,"bm":0,"nm":"Fill 1","mn":"ADBE Vector Graphic - Fill","hd":false},{"ty":"tr","p":{"a":0,"k":[294.09,322.02],"ix":2},"a":{"a":0,"k":[0,0],"ix":1},"s":{"a":0,"k":[100,100],"ix":3},"r":{"a":0,"k":0,"ix":6},"o":{"a":0,"k":100,"ix":7},"sk":{"a":0,"k":0,"ix":4},"sa":{"a":0,"k":0,"ix":5},"nm":"Transform"}],"nm":"Group 9","np":2,"cix":2,"bm":0,"ix":1,"mn":"ADBE Vector Group","hd":false}],"ip":23,"op":106,"st":23,"bm":0},{"ddd":0,"ind":12,"ty":4,"nm":"back-manga2","parent":5,"sr":1,"ks":{"o":{"a":1,"k":[{"i":{"x":[0.667],"y":[1]},"o":{"x":[0.333],"y":[0]},"t":50,"s":[0],"e":[100]},{"t":56}],"ix":11},"r":{"a":0,"k":0,"ix":10},"p":{"a":0,"k":[25.569,33.544,0],"ix":2},"a":{"a":0,"k":[405.96,439.78,0],"ix":1},"s":{"a":0,"k":[24,24,100],"ix":6}},"ao":0,"shapes":[{"ty":"gr","it":[{"ind":0,"ty":"sh","ix":1,"ks":{"a":0,"k":{"i":[[-21.522,0],[0,-6.732],[21.522,0],[0,6.733]],"o":[[21.522,0],[0,6.733],[-21.522,0],[0,-6.732]],"v":[[0,-12.19],[38.97,0],[0,12.19],[-38.97,0]],"c":true},"ix":2},"nm":"Path 1","mn":"ADBE Vector Shape - Group","hd":false},{"ty":"fl","c":{"a":0,"k":[0,0.180000005984,0.395999983245,1],"ix":4},"o":{"a":0,"k":100,"ix":5},"r":1,"bm":0,"nm":"Fill 1","mn":"ADBE Vector Graphic - Fill","hd":false},{"ty":"tr","p":{"a":0,"k":[405.96,439.78],"ix":2},"a":{"a":0,"k":[0,0],"ix":1},"s":{"a":0,"k":[100,100],"ix":3},"r":{"a":0,"k":0,"ix":6},"o":{"a":0,"k":100,"ix":7},"sk":{"a":0,"k":0,"ix":4},"sa":{"a":0,"k":0,"ix":5},"nm":"Transform"}],"nm":"Group 11","np":2,"cix":2,"bm":0,"ix":1,"mn":"ADBE Vector Group","hd":false}],"ip":23,"op":106,"st":23,"bm":0},{"ddd":0,"ind":13,"ty":4,"nm":"t-shirt-shadow","parent":5,"sr":1,"ks":{"o":{"a":1,"k":[{"i":{"x":[0.667],"y":[1]},"o":{"x":[0.333],"y":[0]},"t":50,"s":[0],"e":[100]},{"t":56}],"ix":11},"r":{"a":0,"k":0,"ix":10},"p":{"a":0,"k":[13.905,25.057,0],"ix":2},"a":{"a":0,"k":[357.936,405.459,0],"ix":1},"s":{"a":0,"k":[24,24,100],"ix":6}},"ao":0,"shapes":[{"ty":"gr","it":[{"ty":"gr","it":[{"ind":0,"ty":"sh","ix":1,"ks":{"a":0,"k":{"i":[[0,0],[0,0],[0,0],[0,0],[0,9.75],[-0.05,1.54],[11.411,15.43],[36.74,0.201]],"o":[[0,0],[0,0],[0,0],[9.75,1.29],[0,0],[1.23,-35.311],[-10.771,-14.6],[0,0]],"v":[[-16.14,-80.62],[-87.65,53.911],[-56.18,67.501],[49.06,79.331],[20.91,28.131],[86.42,33.741],[58.85,-46.519],[-10.95,-80.62]],"c":true},"ix":2},"nm":"Path 2","mn":"ADBE Vector Shape - Group","hd":false},{"ty":"tr","p":{"a":0,"k":[0,0],"ix":2},"a":{"a":0,"k":[0,0],"ix":1},"s":{"a":0,"k":[100,100],"ix":3},"r":{"a":0,"k":0,"ix":6},"o":{"a":0,"k":100,"ix":7},"sk":{"a":0,"k":0,"ix":4},"sa":{"a":0,"k":0,"ix":5},"nm":"Transform"}],"nm":"Group 1","np":1,"cix":2,"bm":0,"ix":1,"mn":"ADBE Vector Group","hd":false},{"ty":"mm","mm":4,"nm":"Merge Paths 1","mn":"ADBE Vector Filter - Merge","hd":false},{"ty":"gf","o":{"a":0,"k":100,"ix":10},"r":1,"bm":0,"g":{"p":3,"k":{"a":0,"k":[0,0.016,0.196,0.388,0.503,0.016,0.196,0.388,1,0.016,0.196,0.388,0,0.6,0.5,0.3,1,0],"ix":9}},"s":{"a":0,"k":[100,-1],"ix":5},"e":{"a":0,"k":[-102,-7],"ix":6},"t":1,"nm":"Gradient Fill 1","mn":"ADBE Vector Graphic - G-Fill","hd":false},{"ty":"tr","p":{"a":0,"k":[358.52,406.089],"ix":2},"a":{"a":0,"k":[0,0],"ix":1},"s":{"a":0,"k":[100,100],"ix":3},"r":{"a":0,"k":0,"ix":6},"o":{"a":0,"k":100,"ix":7},"sk":{"a":0,"k":0,"ix":4},"sa":{"a":0,"k":0,"ix":5},"nm":"Transform"}],"nm":"Group 10","np":3,"cix":2,"bm":0,"ix":1,"mn":"ADBE Vector Group","hd":false}],"ip":23,"op":106,"st":23,"bm":0},{"ddd":0,"ind":14,"ty":4,"nm":"hhair","parent":5,"sr":1,"ks":{"o":{"a":0,"k":100,"ix":11},"r":{"a":0,"k":0,"ix":10},"p":{"a":0,"k":[-0.656,-21.347,0],"ix":2},"a":{"a":0,"k":[297.265,208.025,0],"ix":1},"s":{"a":0,"k":[24,24,100],"ix":6}},"ao":0,"shapes":[{"ty":"gr","it":[{"ind":0,"ty":"sh","ix":1,"ks":{"a":0,"k":{"i":[[3.181,8.76],[4.65,5.04],[19.101,3.55],[6.95,-5.28],[0.46,-6.57],[0.118,-0.09],[0.716,0.095],[2.579,-8.98],[-2.76,-7.6],[-0.68,-0.96],[-1.09,13.57],[-43.581,3.53],[-1.09,-26.85],[-0.66,4.69],[-0.199,2.126],[-0.933,3.674]],"o":[[-4.81,-13.26],[-7.52,-8.15],[-17.889,-3.33],[-7.649,5.8],[-0.145,0.035],[-0.599,-0.405],[-6,-0.66],[-1.721,6],[2,5.48],[0,0],[8.111,7.4],[0,0],[0.941,-4.06],[0.319,-2.26],[2.529,-2.823],[1.26,-5.18]],"v":[[54.53,-2.58],[42.66,-27.5],[6.48,-40.87],[-27.3,-40.59],[-37.3,-17.73],[-37.699,-17.54],[-39.699,-18.3],[-54.699,2.87],[-55.76,23.76],[-46.42,38.36],[-32.06,-6.21],[39.041,8.18],[48.77,45.87],[51.211,32.73],[51.99,26.15],[57.26,16.26]],"c":true},"ix":2},"nm":"Path 1","mn":"ADBE Vector Shape - Group","hd":false},{"ty":"fl","c":{"a":0,"k":[0,0.26699999641,0.505999995213,1],"ix":4},"o":{"a":0,"k":100,"ix":5},"r":1,"bm":0,"nm":"Fill 1","mn":"ADBE Vector Graphic - Fill","hd":false},{"ty":"tr","p":{"a":0,"k":[296.9,207.08],"ix":2},"a":{"a":0,"k":[0,0],"ix":1},"s":{"a":0,"k":[100,100],"ix":3},"r":{"a":0,"k":0,"ix":6},"o":{"a":0,"k":100,"ix":7},"sk":{"a":0,"k":0,"ix":4},"sa":{"a":0,"k":0,"ix":5},"nm":"Transform"}],"nm":"Group 12","np":2,"cix":2,"bm":0,"ix":1,"mn":"ADBE Vector Group","hd":false}],"ip":53,"op":106,"st":23,"bm":0},{"ddd":0,"ind":15,"ty":4,"nm":"face","parent":5,"sr":1,"ks":{"o":{"a":1,"k":[{"i":{"x":[0.667],"y":[1]},"o":{"x":[0.333],"y":[0]},"t":52,"s":[0],"e":[100]},{"t":56}],"ix":11},"r":{"a":0,"k":0,"ix":10},"p":{"a":1,"k":[{"i":{"x":0.667,"y":1},"o":{"x":0.333,"y":0},"t":53,"s":[-0.739,-26.437,0],"e":[-0.739,-23.687,0],"to":[0,0.458,0],"ti":[0,-0.458,0]},{"t":89}],"ix":2},"a":{"a":0,"k":[296.922,200.91,0],"ix":1},"s":{"a":0,"k":[24,24,100],"ix":6}},"ao":0,"shapes":[{"ty":"gr","it":[{"ind":0,"ty":"sh","ix":1,"ks":{"a":0,"k":{"i":[[-4.81,-1.8],[-0.751,-0.149],[-1.18,-3.11],[-0.47,-0.98],[-2.165,-3.127],[-1.45,-1.86],[0.77,-8.69],[-18.21,-0.23],[-0.87,12.35],[0,0],[0,0],[0,0],[-1.809,7.418],[-0.39,1.46],[-0.606,0.554],[-1.761,5.322],[4.28,1.95],[0.813,-0.193],[0.051,-0.33],[0.771,-3.44],[0.17,-0.71],[0.1,1.35],[0.04,0.52],[0.08,0.72],[0.209,1.44],[0,0],[8.1,7.39],[3.28,-7.97],[0,0],[0,0],[0,0],[0,0],[0,0],[2.51,3.88],[0.166,-0.014],[0.577,-1.166],[-1.2,-2.47]],"o":[[0.713,0.277],[0.83,2.74],[0.37,0.85],[1.669,3.417],[1,1.43],[-0.77,8.69],[1.56,12.06],[18.81,-0.19],[0,0],[0,0],[0,0],[4.288,-6.318],[0.3,-1.46],[0.722,-0.39],[4.14,-3.779],[1.63,-6],[-0.773,-0.317],[0,0.35],[-0.54,3.87],[-0.159,0.74],[-0.06,-1.45],[0,-0.52],[-0.07,-0.75],[-0.17,-1.57],[-2.661,-17.78],[-43.58,3.53],[-0.89,11.06],[0,0],[0,0],[0,0],[0,0],[0,0],[-0.43,-0.6],[-0.167,-0.014],[-1.23,0.423],[-4.44,7.31],[0.6,1.21]],"v":[[-42.545,-3.31],[-40.345,-2.67],[-37.345,6.13],[-36.095,8.89],[-30.335,18.72],[-26.685,23.72],[-28.975,50],[4.165,75.4],[38.635,49.27],[34.545,24.27],[34.345,23.05],[35.175,21.87],[44.394,1.1],[45.465,-3.27],[47.465,-4.69],[56.465,-18.57],[54.665,-37.3],[52.225,-37.49],[52.104,-36.49],[50.104,-25.57],[49.635,-23.34],[49.385,-27.53],[49.265,-29.05],[49.045,-31.26],[48.475,-35.77],[39.905,-61.01],[-31.195,-75.4],[-44.365,-33.69],[-44.835,-32.56],[-44.835,-32.45],[-45.405,-31.08],[-45.405,-30.97],[-45.465,-30.83],[-51.185,-38.71],[-51.685,-38.71],[-54.505,-36.23],[-50.595,-11.23]],"c":true},"ix":2},"nm":"Path 1","mn":"ADBE Vector Shape - Group","hd":false},{"ty":"fl","c":{"a":0,"k":[0.969000004787,0.698000021542,0.497999991623,1],"ix":4},"o":{"a":0,"k":100,"ix":5},"r":1,"bm":0,"nm":"Fill 1","mn":"ADBE Vector Graphic - Fill","hd":false},{"ty":"tr","p":{"a":0,"k":[295.995,276.31],"ix":2},"a":{"a":0,"k":[0,0],"ix":1},"s":{"a":0,"k":[100,100],"ix":3},"r":{"a":0,"k":0,"ix":6},"o":{"a":0,"k":100,"ix":7},"sk":{"a":0,"k":0,"ix":4},"sa":{"a":0,"k":0,"ix":5},"nm":"Transform"}],"nm":"Group 13","np":2,"cix":2,"bm":0,"ix":1,"mn":"ADBE Vector Group","hd":false}],"ip":23,"op":106,"st":23,"bm":0},{"ddd":0,"ind":16,"ty":4,"nm":"Shape Layer 3","parent":5,"sr":1,"ks":{"o":{"a":0,"k":100,"ix":11},"r":{"a":0,"k":0,"ix":10},"p":{"a":0,"k":[0.467,14.486,0],"ix":2},"a":{"a":0,"k":[0,0,0],"ix":1},"s":{"a":0,"k":[186.916,186.916,100],"ix":6}},"ao":0,"shapes":[{"ty":"gr","it":[{"ind":0,"ty":"sh","ix":1,"ks":{"a":0,"k":{"i":[[0,0],[1.93,2.001],[-9.649,-0.138]],"o":[[0,0],[-2.216,-2.298],[4.382,0.063]],"v":[[-2.5,24],[-12.625,20.375],[-3.657,11.941]],"c":false},"ix":2},"nm":"Path 1","mn":"ADBE Vector Shape - Group","hd":false},{"ty":"st","c":{"a":0,"k":[0.96862745098,0.698039215686,0.498039215686,1],"ix":3},"o":{"a":0,"k":100,"ix":4},"w":{"a":0,"k":3,"ix":5},"lc":2,"lj":1,"ml":4,"bm":0,"nm":"Stroke 1","mn":"ADBE Vector Graphic - Stroke","hd":false},{"ty":"tr","p":{"a":0,"k":[0,0],"ix":2},"a":{"a":0,"k":[0,0],"ix":1},"s":{"a":0,"k":[100,100],"ix":3},"r":{"a":0,"k":0,"ix":6},"o":{"a":0,"k":100,"ix":7},"sk":{"a":0,"k":0,"ix":4},"sa":{"a":0,"k":0,"ix":5},"nm":"Transform"}],"nm":"Shape 1","np":3,"cix":2,"bm":0,"ix":1,"mn":"ADBE Vector Group","hd":false},{"ty":"tm","s":{"a":1,"k":[{"i":{"x":[0.667],"y":[1]},"o":{"x":[0.333],"y":[0]},"t":27,"s":[0],"e":[100]},{"t":56}],"ix":1},"e":{"a":1,"k":[{"i":{"x":[0.667],"y":[1]},"o":{"x":[0.333],"y":[0]},"t":24,"s":[0],"e":[100]},{"t":37}],"ix":2},"o":{"a":0,"k":0,"ix":3},"m":1,"ix":2,"nm":"Trim Paths 1","mn":"ADBE Vector Filter - Trim","hd":false}],"ip":24,"op":106,"st":-107,"bm":0},{"ddd":0,"ind":17,"ty":4,"nm":"brazo-izq","parent":5,"sr":1,"ks":{"o":{"a":0,"k":100,"ix":11},"r":{"a":0,"k":0,"ix":10},"p":{"a":1,"k":[{"i":{"x":0.667,"y":1},"o":{"x":0.333,"y":0},"t":55,"s":[-30.952,44.981,0],"e":[-30.952,47.19,0],"to":[0,0.368,0],"ti":[0,-0.368,0]},{"t":89}],"ix":2},"a":{"a":0,"k":[170.62,496.856,0],"ix":1},"s":{"a":1,"k":[{"i":{"x":[0.667,0.667,0.667],"y":[0.806,0.8,1]},"o":{"x":[0.333,0.333,0.333],"y":[0,0,0]},"t":43,"s":[8,8,100],"e":[24.5,24,100]},{"i":{"x":[0.667,0.667,0.667],"y":[1,1,1]},"o":{"x":[0.333,0.333,0.333],"y":[-0.986,0.493,0]},"t":56,"s":[24.5,24,100],"e":[24,24,100]},{"t":58}],"ix":6}},"ao":0,"shapes":[{"ty":"gr","it":[{"ind":0,"ty":"sh","ix":1,"ks":{"a":1,"k":[{"i":{"x":0.667,"y":1},"o":{"x":0.333,"y":0},"t":43,"s":[{"i":[[0,0],[0,0],[5.784,-3.769],[7.525,-8.636],[0,0],[-9.89,1.3],[0,0],[-10.582,10.344]],"o":[[0,0],[-8.146,-1.71],[-9.939,3.601],[0,0],[0,9.88],[0,0],[8.802,-1.356],[10.734,-10.492]],"v":[[-66.338,-9.161],[-71.905,-14.132],[-95.662,-9.616],[-120.496,5.569],[-125.41,18.413],[-107.52,33.943],[-92.612,32.588],[-67.2,16.269]],"c":true}],"e":[{"i":[[0,0],[0,0],[21.52,0],[7.671,-1.679],[0,0],[-9.89,1.3],[0,0],[4.99,13.931]],"o":[[0,0],[0,-6.73],[-7.853,-0.077],[0,0],[0,9.88],[0,0],[8.802,-1.356],[-4.99,-13.931]],"v":[[-63.39,-11.127],[-69.94,-22.977],[-102.05,-35.167],[-125.41,-32.757],[-125.41,18.413],[-107.52,33.943],[-23.822,20.795],[-0.376,-0.928]],"c":true}]},{"i":{"x":0.667,"y":1},"o":{"x":0.333,"y":0},"t":46,"s":[{"i":[[0,0],[0,0],[21.52,0],[7.671,-1.679],[0,0],[-9.89,1.3],[0,0],[4.99,13.931]],"o":[[0,0],[0,-6.73],[-7.853,-0.077],[0,0],[0,9.88],[0,0],[8.802,-1.356],[-4.99,-13.931]],"v":[[-63.39,-11.127],[-69.94,-22.977],[-102.05,-35.167],[-125.41,-32.757],[-125.41,18.413],[-107.52,33.943],[-23.822,20.795],[-0.376,-0.928]],"c":true}],"e":[{"i":[[0,0],[0,0],[21.52,0],[7.671,-1.679],[0,0],[-9.89,1.3],[0,0],[-1.734,8.736]],"o":[[0,0],[0,-6.73],[-7.853,-0.077],[0,0],[0,9.88],[0,0],[8.802,-1.356],[0,0]],"v":[[-63.39,-11.127],[-69.94,-22.977],[-102.05,-35.167],[-125.41,-32.757],[-125.41,18.413],[-107.52,33.943],[107.86,5.563],[125.41,-11.247]],"c":true}]},{"t":59}],"ix":2},"nm":"Path 1","mn":"ADBE Vector Shape - Group","hd":false},{"ty":"mm","mm":4,"nm":"Merge Paths 1","mn":"ADBE Vector Filter - Merge","hd":false},{"ty":"fl","c":{"a":0,"k":[0.882000014361,0.569000004787,0.352999997606,1],"ix":4},"o":{"a":0,"k":100,"ix":5},"r":1,"bm":0,"nm":"Fill 1","mn":"ADBE Vector Graphic - Fill","hd":false},{"ty":"tr","p":{"a":0,"k":[296.03,462.756],"ix":2},"a":{"a":0,"k":[0,0],"ix":1},"s":{"a":0,"k":[100,100],"ix":3},"r":{"a":0,"k":0,"ix":6},"o":{"a":0,"k":100,"ix":7},"sk":{"a":0,"k":0,"ix":4},"sa":{"a":0,"k":0,"ix":5},"nm":"Transform"}],"nm":"Group 14","np":3,"cix":2,"bm":0,"ix":1,"mn":"ADBE Vector Group","hd":false}],"ip":43,"op":106,"st":23,"bm":0},{"ddd":0,"ind":18,"ty":4,"nm":"tshirt","parent":5,"sr":1,"ks":{"o":{"a":1,"k":[{"i":{"x":[0.667],"y":[1]},"o":{"x":[0.333],"y":[0]},"t":52,"s":[0],"e":[100]},{"t":56}],"ix":11},"r":{"a":0,"k":0,"ix":10},"p":{"a":1,"k":[{"i":{"x":0.667,"y":1},"o":{"x":0.333,"y":0},"t":55,"s":[0.002,23.4,0],"e":[0.002,26.3,0],"to":[0,0,0],"ti":[0,0,0]},{"t":85}],"ix":2},"a":{"a":0,"k":[300.01,409.182,0],"ix":1},"s":{"a":0,"k":[24,24,100],"ix":6}},"ao":0,"shapes":[{"ty":"gr","it":[{"ind":0,"ty":"sh","ix":1,"ks":{"a":0,"k":{"i":[[11.41,15.43],[36.739,0.201],[0,0],[0,0],[18.81,-0.189],[1.69,12],[0.56,0],[0.14,0],[10.77,-14.599],[0,-35.28],[-21.55,0],[0,-6.731],[12.27,-2.05],[-6.94,0.91],[0,0],[0,0],[0,9.75],[-0.05,1.54]],"o":[[-10.771,-14.601],[0,0],[0,0],[-0.87,12.351],[-18.1,-0.239],[-2,0.16],[-2.92,0],[-36.74,0.19],[-11.41,15.53],[0,-6.731],[21.55,0],[0,4.66],[-12.34,18.1],[0,0],[0,0],[9.75,1.29],[0,0],[1.21,-35.271]],"v":[[116.785,-50.055],[46.985,-84.156],[36.715,-84.156],[34.065,-84.156],[-0.405,-58.026],[-33.545,-83.424],[-38.855,-83.326],[-48.995,-83.535],[-117.505,-50.106],[-145.585,30.155],[-106.585,17.965],[-74.475,30.155],[-88.235,40.905],[-114.015,83.245],[1.775,63.924],[107.014,75.755],[78.865,24.555],[144.375,30.165]],"c":true},"ix":2},"nm":"Path 1","mn":"ADBE Vector Shape - Group","hd":false},{"ty":"mm","mm":4,"nm":"Merge Paths 1","mn":"ADBE Vector Filter - Merge","hd":false},{"ty":"fl","c":{"a":0,"k":[0,0.4,0.658999992819,1],"ix":4},"o":{"a":0,"k":100,"ix":5},"r":1,"bm":0,"nm":"Fill 1","mn":"ADBE Vector Graphic - Fill","hd":false},{"ty":"tr","p":{"a":0,"k":[300.585,409.625],"ix":2},"a":{"a":0,"k":[0,0],"ix":1},"s":{"a":0,"k":[100,100],"ix":3},"r":{"a":0,"k":0,"ix":6},"o":{"a":0,"k":100,"ix":7},"sk":{"a":0,"k":0,"ix":4},"sa":{"a":0,"k":0,"ix":5},"nm":"Transform"}],"nm":"Group 15","np":3,"cix":2,"bm":0,"ix":1,"mn":"ADBE Vector Group","hd":false}],"ip":40,"op":106,"st":14,"bm":0},{"ddd":0,"ind":19,"ty":4,"nm":"back-manga","parent":5,"sr":1,"ks":{"o":{"a":1,"k":[{"i":{"x":[0.667],"y":[1]},"o":{"x":[0.333],"y":[0]},"t":52,"s":[0],"e":[100]},{"t":56}],"ix":11},"r":{"a":0,"k":0,"ix":10},"p":{"a":1,"k":[{"i":{"x":0.667,"y":1},"o":{"x":0.333,"y":0},"t":55,"s":[-25.447,30.43,0],"e":[-25.447,33.294,0],"to":[0,0.477,0],"ti":[0,-0.477,0]},{"t":89}],"ix":2},"a":{"a":0,"k":[193.97,439.78,0],"ix":1},"s":{"a":0,"k":[24,24,100],"ix":6}},"ao":0,"shapes":[{"ty":"gr","it":[{"ind":0,"ty":"sh","ix":1,"ks":{"a":0,"k":{"i":[[-21.523,0],[0,-6.732],[21.522,0],[0,6.733]],"o":[[21.522,0],[0,6.733],[-21.523,0],[0,-6.732]],"v":[[0,-12.19],[38.97,0],[0,12.19],[-38.97,0]],"c":true},"ix":2},"nm":"Path 1","mn":"ADBE Vector Shape - Group","hd":false},{"ty":"mm","mm":4,"nm":"Merge Paths 1","mn":"ADBE Vector Filter - Merge","hd":false},{"ty":"fl","c":{"a":0,"k":[0,0.180000005984,0.395999983245,1],"ix":4},"o":{"a":0,"k":100,"ix":5},"r":1,"bm":0,"nm":"Fill 1","mn":"ADBE Vector Graphic - Fill","hd":false},{"ty":"tr","p":{"a":0,"k":[193.97,439.78],"ix":2},"a":{"a":0,"k":[0,0],"ix":1},"s":{"a":0,"k":[100,100],"ix":3},"r":{"a":0,"k":0,"ix":6},"o":{"a":0,"k":100,"ix":7},"sk":{"a":0,"k":0,"ix":4},"sa":{"a":0,"k":0,"ix":5},"nm":"Transform"}],"nm":"Group 16","np":3,"cix":2,"bm":0,"ix":1,"mn":"ADBE Vector Group","hd":false}],"ip":23,"op":106,"st":23,"bm":0},{"ddd":0,"ind":20,"ty":4,"nm":"shadow+","parent":5,"sr":1,"ks":{"o":{"a":1,"k":[{"i":{"x":[0.667],"y":[1]},"o":{"x":[0.333],"y":[0]},"t":54,"s":[0],"e":[100]},{"t":81}],"ix":11},"r":{"a":0,"k":0,"ix":10},"p":{"a":0,"k":[-22.8,45.545,0],"ix":2},"a":{"a":0,"k":[205,489.781,0],"ix":1},"s":{"a":0,"k":[24,24,100],"ix":6}},"ao":0,"shapes":[{"ty":"gr","it":[{"ty":"gr","it":[{"ind":0,"ty":"sh","ix":1,"ks":{"a":0,"k":{"i":[[3.201,-2.432],[0.46,-6.571],[0.119,-0.09],[0.716,0.094],[2.58,-8.98],[-2.76,-7.6],[-1.454,-2.115],[0.166,-0.014],[0.576,-1.167],[-1.2,-2.47],[-4.81,-1.781],[-0.751,-0.149],[-1.18,-3.111],[-0.471,-0.98],[-2.165,-3.127],[-1.45,-1.86],[0.769,-8.69],[0.56,0],[0.14,0],[10.77,-14.6],[0,-35.281],[-9.48,-2.22],[0,0],[-9.89,1.299],[0,0],[0,0],[0,9.88],[0,0],[0,3.99],[1.63,8.07],[0.092,0.454],[0.346,1.488],[0.821,2.487],[0.313,0.887],[3.179,6.063],[0.399,0.733],[0.807,1.373],[0.799,1.293],[1.151,1.69],[1.071,1.45],[3.778,3.489],[1.142,0.953],[1.239,0.919],[1.34,0.886],[9.52,2.287],[7.434,0.011],[0,0],[0,0],[0,0],[0,0],[0,0],[0,0],[-1.811,7.418],[-0.39,1.461],[-0.606,0.553],[-1.76,5.321],[4.28,1.95],[0.808,-0.186],[-0.181,1.8],[-0.933,3.674],[3.18,8.76],[4.649,5.04],[19.099,3.55],[5.534,0.001]],"o":[[-7.65,5.8],[-0.146,0.036],[-0.599,-0.406],[-6,-0.66],[-1.72,6],[0.965,2.378],[-0.167,-0.014],[-1.231,0.422],[-4.44,7.31],[0.61,1.181],[0.713,0.277],[0.831,2.74],[0.37,0.849],[1.668,3.417],[1,1.43],[-0.77,8.69],[-2,0.16],[-2.92,0],[-36.741,0.19],[-11.48,15.58],[0,3.999],[0,0],[0,9.88],[0,0],[0,0],[9.879,1.3],[0,0],[9.48,-2.22],[0.267,-8.228],[-0.092,-0.453],[-0.321,-1.52],[-0.667,-2.665],[-0.292,-0.907],[-2.261,-6.46],[-0.393,-0.754],[-0.794,-1.467],[-0.807,-1.373],[-1.201,-1.92],[-1.149,-1.69],[-3.06,-4.134],[-1.047,-0.967],[-1.139,-0.954],[-1.24,-0.927],[-8.171,-5.395],[-7.23,-1.73],[0,0],[0,0],[0,0],[0,0],[0,0],[0,0],[4.289,-6.317],[0.299,-1.46],[0.723,-0.39],[4.141,-3.779],[1.63,-6.001],[-0.767,-0.316],[0.25,-1.9],[2.528,-2.823],[1.27,-5.181],[-4.81,-13.26],[-7.521,-8.15],[-9.65,-1.796],[-4.727,0]],"v":[[114.66,-273.285],[104.66,-250.426],[104.26,-250.236],[102.26,-250.995],[87.26,-229.826],[86.2,-208.935],[89.84,-202.176],[89.34,-202.176],[86.52,-199.695],[90.43,-174.695],[98.54,-166.826],[100.74,-166.185],[103.74,-157.384],[104.991,-154.625],[110.75,-144.796],[114.4,-139.796],[112.111,-113.516],[106.8,-113.415],[96.66,-113.626],[28.15,-80.195],[0,0.116],[15.62,9.865],[15.62,41.535],[33.51,57.066],[167.81,39.335],[256.43,57.035],[274.32,41.504],[274.32,9.875],[289.941,0.125],[287.889,-24.405],[287.611,-25.766],[286.611,-30.276],[284.379,-38.005],[283.47,-40.695],[275.299,-59.505],[274.111,-61.736],[271.71,-65.996],[269.3,-69.996],[265.759,-75.405],[262.41,-80.116],[252.13,-91.576],[248.849,-94.455],[245.28,-97.265],[241.41,-99.986],[214.67,-111.595],[192.599,-114.215],[187.41,-114.215],[182.33,-114.215],[179.68,-114.215],[175.59,-139.215],[175.389,-140.436],[176.219,-141.616],[185.441,-162.385],[186.51,-166.755],[188.51,-168.174],[197.51,-182.055],[195.71,-200.785],[193.29,-200.986],[193.94,-206.546],[199.21,-216.435],[196.49,-235.275],[184.62,-260.195],[148.441,-273.565],[126.21,-276.676]],"c":true},"ix":2},"nm":"Path 2","mn":"ADBE Vector Shape - Group","hd":false},{"ty":"tr","p":{"a":0,"k":[0,0],"ix":2},"a":{"a":0,"k":[0,0],"ix":1},"s":{"a":0,"k":[100,100],"ix":3},"r":{"a":0,"k":0,"ix":6},"o":{"a":0,"k":100,"ix":7},"sk":{"a":0,"k":0,"ix":4},"sa":{"a":0,"k":0,"ix":5},"nm":"Transform"}],"nm":"Group 1","np":1,"cix":2,"bm":0,"ix":1,"mn":"ADBE Vector Group","hd":false},{"ty":"mm","mm":4,"nm":"Merge Paths 1","mn":"ADBE Vector Filter - Merge","hd":false},{"ty":"gf","o":{"a":0,"k":100,"ix":10},"r":1,"bm":0,"g":{"p":3,"k":{"a":0,"k":[0,0.098,0.149,0.278,0.503,0.098,0.149,0.278,1,0.098,0.149,0.278,0,0.5,0.5,0.25,1,0],"ix":9}},"s":{"a":0,"k":[25,-240],"ix":5},"e":{"a":0,"k":[232,93],"ix":6},"t":1,"nm":"Gradient Fill 1","mn":"ADBE Vector Graphic - G-Fill","hd":false},{"ty":"tr","p":{"a":0,"k":[205,489.665],"ix":2},"a":{"a":0,"k":[0,0],"ix":1},"s":{"a":0,"k":[100,100],"ix":3},"r":{"a":0,"k":0,"ix":6},"o":{"a":0,"k":100,"ix":7},"sk":{"a":0,"k":0,"ix":4},"sa":{"a":0,"k":0,"ix":5},"nm":"Transform"}],"nm":"Group 17","np":3,"cix":2,"bm":0,"ix":1,"mn":"ADBE Vector Group","hd":false}],"ip":23,"op":106,"st":23,"bm":0},{"ddd":0,"ind":21,"ty":3,"nm":"Null 6","parent":30,"sr":1,"ks":{"o":{"a":0,"k":0,"ix":11},"r":{"a":0,"k":0,"ix":10},"p":{"a":0,"k":[0.406,-14.422,0],"ix":2},"a":{"a":0,"k":[0,0,0],"ix":1},"s":{"a":0,"k":[24,24,100],"ix":6}},"ao":0,"ip":0,"op":55,"st":-107,"bm":0},{"ddd":0,"ind":22,"ty":4,"nm":"rojo 2","sr":1,"ks":{"o":{"a":0,"k":100,"ix":11},"r":{"a":0,"k":0,"ix":10},"p":{"a":0,"k":[72,72,0],"ix":2},"a":{"a":0,"k":[0,0,0],"ix":1},"s":{"a":0,"k":[100,100,100],"ix":6}},"ao":0,"shapes":[{"ty":"gr","it":[{"ind":0,"ty":"sh","ix":1,"ks":{"a":0,"k":{"i":[[0,0],[-38.5,3]],"o":[[0,0],[37.862,-2.95]],"v":[[0.375,26.25],[-10.125,15.25]],"c":false},"ix":2},"nm":"Path 1","mn":"ADBE Vector Shape - Group","hd":false},{"ty":"tm","s":{"a":1,"k":[{"i":{"x":[0.667],"y":[0.733]},"o":{"x":[0.333],"y":[0]},"t":18,"s":[2.8],"e":[100]},{"i":{"x":[0.667],"y":[1]},"o":{"x":[0.333],"y":[27.344]},"t":37,"s":[100],"e":[100]},{"t":57}],"ix":1},"e":{"a":1,"k":[{"i":{"x":[0.833],"y":[1]},"o":{"x":[0.333],"y":[0]},"t":28,"s":[0],"e":[100]},{"t":51}],"ix":2},"o":{"a":0,"k":0,"ix":3},"m":1,"ix":2,"nm":"Trim Paths 1","mn":"ADBE Vector Filter - Trim","hd":false},{"ty":"st","c":{"a":1,"k":[{"i":{"x":[0.833],"y":[1]},"o":{"x":[0.333],"y":[0]},"t":18,"s":[0.854901960784,0.223529411765,0.317647058824,1],"e":[0.854902020623,0.223529426724,0.317647058824,1]},{"i":{"x":[0.667],"y":[1]},"o":{"x":[0.333],"y":[0]},"t":29,"s":[0.854902020623,0.223529426724,0.317647058824,1],"e":[0.882352948189,0.568627476692,0.352941185236,1]},{"t":41}],"ix":3},"o":{"a":0,"k":100,"ix":4},"w":{"a":1,"k":[{"i":{"x":[0.833],"y":[1]},"o":{"x":[0.167],"y":[0]},"t":3,"s":[9],"e":[8.33]},{"i":{"x":[0.833],"y":[1]},"o":{"x":[0.167],"y":[0]},"t":18,"s":[8.33],"e":[8.3]},{"i":{"x":[0.667],"y":[1]},"o":{"x":[0.167],"y":[0]},"t":22,"s":[8.3],"e":[2]},{"t":53}],"ix":5},"lc":2,"lj":1,"ml":4,"bm":0,"nm":"Stroke 1","mn":"ADBE Vector Graphic - Stroke","hd":false},{"ty":"tr","p":{"a":0,"k":[0,0],"ix":2},"a":{"a":0,"k":[0,0],"ix":1},"s":{"a":0,"k":[100,100],"ix":3},"r":{"a":0,"k":0,"ix":6},"o":{"a":0,"k":100,"ix":7},"sk":{"a":0,"k":0,"ix":4},"sa":{"a":0,"k":0,"ix":5},"nm":"Transform"}],"nm":"Shape 1","np":4,"cix":2,"bm":0,"ix":1,"mn":"ADBE Vector Group","hd":false}],"ip":0,"op":58,"st":-107,"bm":0},{"ddd":0,"ind":23,"ty":4,"nm":"Group 21","parent":21,"sr":1,"ks":{"o":{"a":0,"k":100,"ix":11},"r":{"a":0,"k":0,"ix":10},"p":{"a":0,"k":[-61.1,53.742,0],"ix":2},"a":{"a":0,"k":[240.604,295.992,0],"ix":1},"s":{"a":0,"k":[100,100,100],"ix":6}},"ao":0,"shapes":[{"ty":"gr","it":[{"ind":0,"ty":"sh","ix":1,"ks":{"a":0,"k":{"i":[[0,0],[0,0],[0,0]],"o":[[0,0],[0,0],[0,0]],"v":[[19.475,19.475],[-19.476,19.475],[-19.476,-19.475]],"c":false},"ix":2},"nm":"Path 1","mn":"ADBE Vector Shape - Group","hd":false},{"ty":"st","c":{"a":0,"k":[0.972999961703,0.804000016755,0.313999998803,1],"ix":3},"o":{"a":0,"k":100,"ix":4},"w":{"a":0,"k":7.2,"ix":5},"lc":2,"lj":2,"bm":0,"nm":"Stroke 1","mn":"ADBE Vector Graphic - Stroke","hd":false},{"ty":"tr","p":{"a":0,"k":[260.079,276.516],"ix":2},"a":{"a":0,"k":[0,0],"ix":1},"s":{"a":0,"k":[100,100],"ix":3},"r":{"a":0,"k":0,"ix":6},"o":{"a":0,"k":100,"ix":7},"sk":{"a":0,"k":0,"ix":4},"sa":{"a":0,"k":0,"ix":5},"nm":"Transform"}],"nm":"Group 1","np":2,"cix":2,"bm":0,"ix":1,"mn":"ADBE Vector Group","hd":false},{"ty":"tm","s":{"a":1,"k":[{"i":{"x":[0.833],"y":[1]},"o":{"x":[0.167],"y":[0]},"t":8,"s":[0],"e":[100]},{"t":12}],"ix":1},"e":{"a":0,"k":100,"ix":2},"o":{"a":0,"k":0,"ix":3},"m":1,"ix":2,"nm":"Trim Paths 1","mn":"ADBE Vector Filter - Trim","hd":false}],"ip":0,"op":14,"st":-107,"bm":0},{"ddd":0,"ind":24,"ty":4,"nm":"Group 20","parent":21,"sr":1,"ks":{"o":{"a":0,"k":100,"ix":11},"r":{"a":0,"k":0,"ix":10},"p":{"a":0,"k":[29.6,34.266,0],"ix":2},"a":{"a":0,"k":[331.331,276.516,0],"ix":1},"s":{"a":0,"k":[100,100,100],"ix":6}},"ao":0,"shapes":[{"ty":"gr","it":[{"ind":0,"ty":"sh","ix":1,"ks":{"a":0,"k":{"i":[[0,0],[0,0],[0,0]],"o":[[0,0],[0,0],[0,0]],"v":[[19.475,-19.475],[19.475,19.476],[-19.476,19.476]],"c":false},"ix":2},"nm":"Path 1","mn":"ADBE Vector Shape - Group","hd":false},{"ty":"st","c":{"a":0,"k":[0.972999961703,0.804000016755,0.313999998803,1],"ix":3},"o":{"a":0,"k":100,"ix":4},"w":{"a":0,"k":7.2,"ix":5},"lc":2,"lj":2,"bm":0,"nm":"Stroke 1","mn":"ADBE Vector Graphic - Stroke","hd":false},{"ty":"tr","p":{"a":0,"k":[331.331,276.516],"ix":2},"a":{"a":0,"k":[0,0],"ix":1},"s":{"a":0,"k":[100,100],"ix":3},"r":{"a":0,"k":0,"ix":6},"o":{"a":0,"k":100,"ix":7},"sk":{"a":0,"k":0,"ix":4},"sa":{"a":0,"k":0,"ix":5},"nm":"Transform"}],"nm":"Group 2","np":2,"cix":2,"bm":0,"ix":1,"mn":"ADBE Vector Group","hd":false},{"ty":"tm","s":{"a":1,"k":[{"i":{"x":[0.667],"y":[1]},"o":{"x":[0.333],"y":[0]},"t":4,"s":[0],"e":[100]},{"t":9}],"ix":1},"e":{"a":0,"k":100,"ix":2},"o":{"a":0,"k":0,"ix":3},"m":1,"ix":2,"nm":"Trim Paths 1","mn":"ADBE Vector Filter - Trim","hd":false}],"ip":0,"op":12,"st":-107,"bm":0},{"ddd":0,"ind":25,"ty":4,"nm":"Group 19","parent":21,"sr":1,"ks":{"o":{"a":0,"k":100,"ix":11},"r":{"a":0,"k":0,"ix":10},"p":{"a":0,"k":[29.6,-37.936,0],"ix":2},"a":{"a":0,"k":[331.331,204.314,0],"ix":1},"s":{"a":0,"k":[100,100,100],"ix":6}},"ao":0,"shapes":[{"ty":"gr","it":[{"ind":0,"ty":"sh","ix":1,"ks":{"a":0,"k":{"i":[[0,0],[0,0],[0,0]],"o":[[0,0],[0,0],[0,0]],"v":[[-19.475,-19.476],[19.475,-19.476],[19.475,19.476]],"c":false},"ix":2},"nm":"Path 1","mn":"ADBE Vector Shape - Group","hd":false},{"ty":"st","c":{"a":0,"k":[0.972999961703,0.804000016755,0.313999998803,1],"ix":3},"o":{"a":0,"k":100,"ix":4},"w":{"a":0,"k":7.2,"ix":5},"lc":2,"lj":2,"bm":0,"nm":"Stroke 1","mn":"ADBE Vector Graphic - Stroke","hd":false},{"ty":"tr","p":{"a":0,"k":[331.331,204.314],"ix":2},"a":{"a":0,"k":[0,0],"ix":1},"s":{"a":0,"k":[100,100],"ix":3},"r":{"a":0,"k":0,"ix":6},"o":{"a":0,"k":100,"ix":7},"sk":{"a":0,"k":0,"ix":4},"sa":{"a":0,"k":0,"ix":5},"nm":"Transform"}],"nm":"Group 3","np":2,"cix":2,"bm":0,"ix":1,"mn":"ADBE Vector Group","hd":false},{"ty":"tm","s":{"a":0,"k":0,"ix":1},"e":{"a":1,"k":[{"i":{"x":[0.833],"y":[1]},"o":{"x":[0.167],"y":[0]},"t":0,"s":[100],"e":[50]},{"t":7}],"ix":2},"o":{"a":0,"k":0,"ix":3},"m":1,"ix":2,"nm":"Trim Paths 1","mn":"ADBE Vector Filter - Trim","hd":false}],"ip":0,"op":25,"st":-107,"bm":0},{"ddd":0,"ind":26,"ty":4,"nm":"Group 18","parent":21,"sr":1,"ks":{"o":{"a":0,"k":100,"ix":11},"r":{"a":0,"k":0,"ix":10},"p":{"a":0,"k":[-41.7,-37.936,0],"ix":2},"a":{"a":0,"k":[260.079,204.314,0],"ix":1},"s":{"a":0,"k":[100,100,100],"ix":6}},"ao":0,"shapes":[{"ty":"gr","it":[{"ind":0,"ty":"sh","ix":1,"ks":{"a":0,"k":{"i":[[0,0],[0,0],[0,0]],"o":[[0,0],[0,0],[0,0]],"v":[[-19.475,19.475],[-19.475,-19.475],[19.475,-19.475]],"c":false},"ix":2},"nm":"Path 1","mn":"ADBE Vector Shape - Group","hd":false},{"ty":"st","c":{"a":0,"k":[0.972999961703,0.804000016755,0.313999998803,1],"ix":3},"o":{"a":0,"k":100,"ix":4},"w":{"a":0,"k":7.2,"ix":5},"lc":2,"lj":2,"bm":0,"nm":"Stroke 1","mn":"ADBE Vector Graphic - Stroke","hd":false},{"ty":"tr","p":{"a":0,"k":[260.079,204.314],"ix":2},"a":{"a":0,"k":[0,0],"ix":1},"s":{"a":0,"k":[100,100],"ix":3},"r":{"a":0,"k":0,"ix":6},"o":{"a":0,"k":100,"ix":7},"sk":{"a":0,"k":0,"ix":4},"sa":{"a":0,"k":0,"ix":5},"nm":"Transform"}],"nm":"Group 4","np":2,"cix":2,"bm":0,"ix":1,"mn":"ADBE Vector Group","hd":false},{"ty":"tm","s":{"a":0,"k":0,"ix":1},"e":{"a":0,"k":100,"ix":2},"o":{"a":0,"k":0,"ix":3},"m":1,"ix":2,"nm":"Trim Paths 1","mn":"ADBE Vector Filter - Trim","hd":false}],"ip":0,"op":16,"st":-107,"bm":0},{"ddd":0,"ind":27,"ty":3,"nm":"man 2","sr":1,"ks":{"o":{"a":0,"k":0,"ix":11},"r":{"a":0,"k":0,"ix":10},"p":{"a":0,"k":[72,72,0],"ix":2},"a":{"a":0,"k":[0,0,0],"ix":1},"s":{"a":0,"k":[100,100,100],"ix":6}},"ao":0,"ip":0,"op":46,"st":-107,"bm":0},{"ddd":0,"ind":28,"ty":4,"nm":"head 3","parent":27,"sr":1,"ks":{"o":{"a":0,"k":100,"ix":11},"r":{"a":0,"k":0,"ix":10},"p":{"a":1,"k":[{"i":{"x":0.833,"y":0.833},"o":{"x":0.333,"y":0.333},"t":4,"s":[-0.94,-16.227,0],"e":[-0.94,-16.227,0],"to":[0,0,0],"ti":[0,0,0]},{"i":{"x":0.498,"y":1},"o":{"x":0.333,"y":0},"t":23,"s":[-0.94,-16.227,0],"e":[-0.9,-27.227,0],"to":[0.007,-1.833,0],"ti":[-0.083,0.083,0]},{"i":{"x":0.339,"y":1},"o":{"x":0.589,"y":0},"t":25,"s":[-0.9,-27.227,0],"e":[-0.44,-16.727,0],"to":[0.083,-0.083,0],"ti":[-0.077,-1.75,0]},{"t":54}],"ix":2},"a":{"a":0,"k":[298.604,237.057,0],"ix":1},"s":{"a":0,"k":[24,24,100],"ix":6}},"ao":0,"shapes":[{"ty":"gr","it":[{"ind":0,"ty":"sh","ix":1,"ks":{"a":0,"k":{"i":[[0,0],[0,0],[0,0],[-0.938,3.847],[-0.21,0.761],[-0.303,0.285],[-0.921,2.762],[2.221,1.009],[0.42,-0.099],[-0.09,0.93],[-0.483,1.905],[1.65,4.54],[2.42,2.61],[9.9,1.839],[3.61,-2.73],[0.22,-3.4],[0.062,-0.047],[0.38,0.047],[1.34,-4.681],[-1.45,-3.94],[-0.755,-1.096],[0.086,-0.008],[0.3,-0.601],[-0.59,-1.319],[-1.834,-0.83],[-0.389,-0.077],[-0.62,-1.56],[-0.24,-0.509],[-1.127,-1.619],[-0.75,-0.951],[-13.167,0]],"o":[[0,0],[0,0],[2.223,-3.275],[0.16,-0.759],[0.362,-0.205],[2.154,-1.959],[0.85,-3.121],[-0.398,-0.165],[0.13,-1],[1.31,-1.465],[0.659,-2.68],[-2.5,-6.87],[-3.9,-4.22],[-9.28,-1.73],[-4,3],[-0.076,0.019],[-0.317,-0.215],[-3.12,-0.34],[-0.89,3.109],[0.502,1.231],[-0.086,-0.008],[-0.636,0.218],[-2.3,3.79],[0.888,1.808],[0.369,0.144],[0.43,1.419],[0.19,0.44],[0.87,1.77],[0.51,0.739],[0,0],[8.5,0]],"v":[[18.691,48.609],[18.882,32.521],[18.792,29.307],[22.921,21.141],[23.48,18.871],[24.48,18.132],[29.171,10.932],[28.24,1.222],[26.98,1.121],[27.311,-1.758],[30.041,-6.888],[28.631,-16.658],[22.471,-29.578],[3.711,-36.508],[-13.809,-36.368],[-18.969,-24.519],[-19.179,-24.419],[-20.239,-24.818],[-28.019,-13.818],[-28.569,-2.988],[-26.679,0.512],[-26.939,0.512],[-28.399,1.791],[-26.399,14.791],[-22.189,18.871],[-21.049,19.202],[-19.489,23.762],[-18.839,25.191],[-14.407,31.975],[-14.34,47.576],[1.67,52.249]],"c":true},"ix":2},"nm":"Path 1","mn":"ADBE Vector Shape - Group","hd":false},{"ty":"fl","c":{"a":0,"k":[0,0.26699999641,0.505999995213,1],"ix":4},"o":{"a":0,"k":100,"ix":5},"r":1,"bm":0,"nm":"Fill 1","mn":"ADBE Vector Graphic - Fill","hd":false},{"ty":"tr","p":{"a":0,"k":[298.07,236.568],"ix":2},"a":{"a":0,"k":[0,0],"ix":1},"s":{"a":0,"k":[100,100],"ix":3},"r":{"a":0,"k":0,"ix":6},"o":{"a":0,"k":100,"ix":7},"sk":{"a":0,"k":0,"ix":4},"sa":{"a":0,"k":0,"ix":5},"nm":"Transform"}],"nm":"Group 1","np":2,"cix":2,"bm":0,"ix":1,"mn":"ADBE Vector Group","hd":false}],"ip":0,"op":56,"st":-60,"bm":0},{"ddd":0,"ind":29,"ty":4,"nm":"body 4","parent":27,"sr":1,"ks":{"o":{"a":0,"k":100,"ix":11},"r":{"a":0,"k":0,"ix":10},"p":{"a":1,"k":[{"i":{"x":0.667,"y":1},"o":{"x":0.333,"y":0},"t":4,"s":[-0.343,22.25,0],"e":[-0.343,22.041,0],"to":[0,0,0],"ti":[0,0,0]},{"i":{"x":0.667,"y":1},"o":{"x":0.333,"y":0},"t":23,"s":[-0.343,22.041,0],"e":[-0.3,11.541,0],"to":[0.042,-1.792,0],"ti":[-0.042,0.458,0]},{"i":{"x":0.339,"y":1},"o":{"x":0.589,"y":0},"t":25,"s":[-0.3,11.541,0],"e":[-0.093,19.291,0],"to":[0.042,-0.458,0],"ti":[-0.035,-1.25,0]},{"i":{"x":0.833,"y":0.833},"o":{"x":0.167,"y":0.167},"t":54,"s":[-0.093,19.291,0],"e":[-0.093,19.041,0],"to":[0.035,1.25,0],"ti":[0,0.042,0]},{"t":55}],"ix":2},"a":{"a":0,"k":[300.05,327.107,0],"ix":1},"s":{"a":1,"k":[{"i":{"x":[0.667,0.667,0.667],"y":[1,1,1]},"o":{"x":[0.167,0.167,0.167],"y":[0,0,0]},"t":1,"s":[26,26.5,100],"e":[26.5,27,100]},{"i":{"x":[0.833,0.833,0.833],"y":[1,1,1]},"o":{"x":[0.333,0.333,0.333],"y":[0,0,0]},"t":50,"s":[26.5,27,100],"e":[24.8,25,100]},{"t":54}],"ix":6}},"ao":0,"shapes":[{"ty":"gr","it":[{"ind":0,"ty":"sh","ix":1,"ks":{"a":0,"k":{"i":[[0,0],[0.29,0],[0.09,0],[5.58,-7.571],[0,-18.299],[0,0],[0,0],[-4.92,-1.149],[0,0],[-4.418,-0.085],[-0.475,0.076],[0,0],[0,0],[-0.708,4.361],[0.01,0.48],[0,0],[0,2.059],[0.873,4.185],[0,0],[0.193,0.774],[0.426,1.3],[0.16,0.46],[1.649,3.143],[0,0],[0.419,0.714],[0.414,0.66],[0.6,0.881],[0.561,0.75],[1.959,1.809],[0.593,0.494],[0.62,0.48],[0.667,0.46],[4.934,1.181],[3.854,0.006],[0,0]],"o":[[-1,0.08],[-1.51,0],[-19,0.1],[-5.92,8],[0,0],[0,0],[0,2.071],[0,0],[-0.085,4.418],[0.48,0.009],[0,0],[0,0],[4.362,0.707],[0.077,-0.474],[0,0],[4.92,-1.15],[0.114,-4.274],[0,0],[-0.167,-0.787],[-0.347,-1.367],[-0.154,-0.473],[-1.174,-3.349],[0,0],[-0.414,-0.76],[-0.42,-0.713],[-0.621,-1],[-0.6,-0.88],[-1.586,-2.142],[-0.539,-0.5],[-0.594,-0.493],[-0.667,-0.48],[-4.237,-2.789],[-3.747,-0.897],[0,0],[0,0]],"v":[[-17.167,-44.359],[-19.917,-44.309],[-25.177,-44.419],[-60.697,-27.088],[-75.257,14.501],[-75.257,14.381],[-75.257,14.501],[-67.157,19.561],[-67.157,35.981],[-59.312,44.133],[-57.877,44.032],[11.763,34.851],[57.763,44.032],[66.941,37.416],[67.042,35.981],[67.042,19.591],[75.143,14.532],[74.002,1.801],[73.863,1.091],[73.323,-1.249],[72.163,-5.249],[71.693,-6.649],[67.453,-16.399],[66.833,-17.559],[65.583,-19.769],[64.333,-21.829],[62.493,-24.639],[60.752,-27.079],[55.422,-33.019],[53.723,-34.509],[51.903,-35.969],[49.903,-37.379],[36.042,-43.379],[24.603,-44.739],[17.903,-44.739]],"c":true},"ix":2},"nm":"Path 1","mn":"ADBE Vector Shape - Group","hd":false},{"ty":"fl","c":{"a":0,"k":[0,0.26699999641,0.505999995213,1],"ix":4},"o":{"a":0,"k":100,"ix":5},"r":1,"bm":0,"nm":"Fill 1","mn":"ADBE Vector Graphic - Fill","hd":false},{"ty":"tr","p":{"a":0,"k":[300.097,268.925],"ix":2},"a":{"a":0,"k":[0,0],"ix":1},"s":{"a":0,"k":[100,100],"ix":3},"r":{"a":0,"k":0,"ix":6},"o":{"a":0,"k":100,"ix":7},"sk":{"a":0,"k":0,"ix":4},"sa":{"a":0,"k":0,"ix":5},"nm":"Transform"}],"nm":"Group 2","np":2,"cix":2,"bm":0,"ix":1,"mn":"ADBE Vector Group","hd":false}],"ip":0,"op":56,"st":-61,"bm":0},{"ddd":0,"ind":30,"ty":3,"nm":"cel 2","sr":1,"ks":{"o":{"a":0,"k":0,"ix":11},"r":{"a":0,"k":0,"ix":10},"p":{"a":0,"k":[72,72,0],"ix":2},"a":{"a":0,"k":[0,0,0],"ix":1},"s":{"a":0,"k":[100,100,100],"ix":6}},"ao":0,"ip":0,"op":46,"st":-107,"bm":0},{"ddd":0,"ind":31,"ty":4,"nm":"reflejo","parent":30,"sr":1,"ks":{"o":{"a":0,"k":50,"ix":11},"r":{"a":0,"k":0,"ix":10},"p":{"a":0,"k":[-1,-38.274,0],"ix":2},"a":{"a":0,"k":[300,149.9,0],"ix":1},"s":{"a":1,"k":[{"i":{"x":[0.667,0.667,0.667],"y":[1,1,1]},"o":{"x":[0.333,0.333,0.333],"y":[0,0,0]},"t":16,"s":[25.8,25.5,100],"e":[24,1,100]},{"t":36}],"ix":6}},"ao":0,"shapes":[{"ty":"gr","it":[{"ty":"gr","it":[{"ind":0,"ty":"sh","ix":1,"ks":{"a":0,"k":{"i":[[0,0],[0,0],[0,0],[0,0],[0,0]],"o":[[0,0],[0,0],[0,0],[0,0],[0,0]],"v":[[-113,150.1],[-32.833,150.2],[112.877,-120.66],[113,-150.1],[-113,-150.1]],"c":true},"ix":2},"nm":"Path 3","mn":"ADBE Vector Shape - Group","hd":false},{"ty":"rd","nm":"Round Corners 1","r":{"a":0,"k":0,"ix":1},"ix":2,"mn":"ADBE Vector Filter - RC","hd":false},{"ty":"tr","p":{"a":0,"k":[0,0],"ix":2},"a":{"a":0,"k":[0,0],"ix":1},"s":{"a":0,"k":[100,100],"ix":3},"r":{"a":0,"k":0,"ix":6},"o":{"a":0,"k":100,"ix":7},"sk":{"a":0,"k":0,"ix":4},"sa":{"a":0,"k":0,"ix":5},"nm":"Transform"}],"nm":"Group 1","np":2,"cix":2,"bm":0,"ix":1,"mn":"ADBE Vector Group","hd":false},{"ty":"gf","o":{"a":0,"k":50,"ix":10},"r":1,"bm":0,"g":{"p":3,"k":{"a":0,"k":[0,0.981,0.981,0.981,0.502,0.949,0.971,0.973,0.997,0.918,0.961,0.965,0,0.5,0.5,0.3,0.999,0.1],"ix":9}},"s":{"a":0,"k":[-62,-92],"ix":5},"e":{"a":0,"k":[53,72],"ix":6},"t":1,"nm":"Gradient Fill 1","mn":"ADBE Vector Graphic - G-Fill","hd":false},{"ty":"tr","p":{"a":0,"k":[300,300],"ix":2},"a":{"a":0,"k":[0,0],"ix":1},"s":{"a":0,"k":[100,100],"ix":3},"r":{"a":0,"k":0,"ix":6},"o":{"a":0,"k":100,"ix":7},"sk":{"a":0,"k":0,"ix":4},"sa":{"a":0,"k":0,"ix":5},"nm":"Transform"}],"nm":"Group 3","np":2,"cix":2,"bm":0,"ix":1,"mn":"ADBE Vector Group","hd":false}],"ip":0,"op":36,"st":-109,"bm":0},{"ddd":0,"ind":32,"ty":4,"nm":"pantalla","parent":30,"sr":1,"ks":{"o":{"a":0,"k":100,"ix":11},"r":{"a":0,"k":0,"ix":10},"p":{"a":1,"k":[{"i":{"x":0.667,"y":1},"o":{"x":0.333,"y":0},"t":1,"s":[-1.025,-0.059,0],"e":[-1.025,-0.059,0],"to":[0.249,-0.083,0],"ti":[-0.25,0.083,0]},{"i":{"x":0.667,"y":1},"o":{"x":0.333,"y":0},"t":18,"s":[-1.025,-0.059,0],"e":[-0.9,-37.809,0],"to":[0.249,-0.083,0],"ti":[-0.021,6.292,0]},{"t":35}],"ix":2},"a":{"a":0,"k":[0.475,-0.75,0],"ix":1},"s":{"a":1,"k":[{"i":{"x":[0.833,0.833,0.833],"y":[1,1,1]},"o":{"x":[0.333,0.333,0.333],"y":[0,0,0]},"t":1,"s":[106,105,100],"e":[106,105.5,100]},{"i":{"x":[0.667,0.667,0.667],"y":[1,1,1]},"o":{"x":[0.333,0.333,0.333],"y":[0,0,0]},"t":17,"s":[106,105.5,100],"e":[106,112.973,100]},{"i":{"x":[0.667,0.667,0.667],"y":[1,1,1]},"o":{"x":[0.333,0.333,0.333],"y":[0,0,0]},"t":20,"s":[106,112.973,100],"e":[106,5,100]},{"t":35}],"ix":6}},"ao":0,"shapes":[{"ty":"gr","it":[{"ty":"rc","d":1,"s":{"a":0,"k":[55.949,75],"ix":2},"p":{"a":0,"k":[0,0],"ix":3},"r":{"a":1,"k":[{"i":{"x":[0.667],"y":[1]},"o":{"x":[0.333],"y":[0]},"t":20,"s":[0],"e":[24]},{"t":35}],"ix":4},"nm":"Rectangle Path 1","mn":"ADBE Vector Shape - Rect","hd":false},{"ty":"fl","c":{"a":0,"k":[0.286274509804,0.647058823529,0.901960784314,1],"ix":4},"o":{"a":0,"k":100,"ix":5},"r":1,"bm":0,"nm":"Fill 1","mn":"ADBE Vector Graphic - Fill","hd":false},{"ty":"tr","p":{"a":0,"k":[0.475,-0.75],"ix":2},"a":{"a":0,"k":[0,0],"ix":1},"s":{"a":0,"k":[97.887,96.375],"ix":3},"r":{"a":0,"k":0,"ix":6},"o":{"a":0,"k":100,"ix":7},"sk":{"a":0,"k":0,"ix":4},"sa":{"a":0,"k":0,"ix":5},"nm":"Transform"}],"nm":"Rectangle 1","np":3,"cix":2,"bm":0,"ix":1,"mn":"ADBE Vector Group","hd":false}],"ip":0,"op":35,"st":-106,"bm":0},{"ddd":0,"ind":33,"ty":4,"nm":"body-3","parent":30,"sr":1,"ks":{"o":{"a":0,"k":100,"ix":11},"r":{"a":0,"k":0,"ix":10},"p":{"a":1,"k":[{"i":{"x":0.833,"y":1},"o":{"x":0.333,"y":0},"t":24,"s":[0.508,1.338,0],"e":[0.508,-35.912,0],"to":[0,-6.208,0],"ti":[0,6.208,0]},{"t":35}],"ix":2},"a":{"a":0,"k":[0.258,-0.476,0],"ix":1},"s":{"a":1,"k":[{"i":{"x":[0.667,0.667,0.667],"y":[1,1,1]},"o":{"x":[0.333,0.333,0.333],"y":[0,0,0]},"t":3,"s":[100,103,100],"e":[100,107.352,100]},{"i":{"x":[0.667,0.667,0.667],"y":[1,1,1]},"o":{"x":[0.333,0.333,0.333],"y":[0,0,0]},"t":18,"s":[100,107.352,100],"e":[100,107.352,100]},{"i":{"x":[0.667,0.667,0.667],"y":[1,1,1]},"o":{"x":[0.333,0.333,0.333],"y":[0,0,0]},"t":21,"s":[100,107.352,100],"e":[100,4.455,100]},{"t":35}],"ix":6}},"ao":0,"shapes":[{"ty":"gr","it":[{"ty":"rc","d":1,"s":{"a":0,"k":[58,101],"ix":2},"p":{"a":0,"k":[0,0],"ix":3},"r":{"a":1,"k":[{"i":{"x":[0.667],"y":[1]},"o":{"x":[0.333],"y":[0]},"t":21,"s":[5],"e":[38]},{"t":35}],"ix":4},"nm":"Rectangle Path 1","mn":"ADBE Vector Shape - Rect","hd":false},{"ty":"fl","c":{"a":0,"k":[0.078000005086,0.39199999641,0.647000002394,1],"ix":4},"o":{"a":0,"k":100,"ix":5},"r":1,"bm":0,"nm":"Fill 1","mn":"ADBE Vector Graphic - Fill","hd":false},{"ty":"tr","p":{"a":0,"k":[-1.242,-2.226],"ix":2},"a":{"a":0,"k":[0,0],"ix":1},"s":{"a":0,"k":[100,98.722],"ix":3},"r":{"a":0,"k":0,"ix":6},"o":{"a":0,"k":100,"ix":7},"sk":{"a":0,"k":0,"ix":4},"sa":{"a":0,"k":0,"ix":5},"nm":"Transform"}],"nm":"Rectangle 1","np":3,"cix":2,"bm":0,"ix":1,"mn":"ADBE Vector Group","hd":false}],"ip":0,"op":35,"st":-107,"bm":0},{"ddd":0,"ind":34,"ty":4,"nm":"body 3","parent":30,"sr":1,"ks":{"o":{"a":1,"k":[{"i":{"x":[0.667],"y":[1]},"o":{"x":[0.333],"y":[0]},"t":19,"s":[100],"e":[0]},{"t":28}],"ix":11},"r":{"a":0,"k":0,"ix":10},"p":{"a":0,"k":[13.508,-38.737,0],"ix":2},"a":{"a":0,"k":[0.258,-57.373,0],"ix":1},"s":{"a":1,"k":[{"i":{"x":[0.833,0.833,0.833],"y":[1,1,1]},"o":{"x":[0.167,0.167,0.167],"y":[0,0,0]},"t":1,"s":[98.5,106,100],"e":[100,106,100]},{"i":{"x":[0.667,0.667,0.667],"y":[1,0.345,1]},"o":{"x":[0.333,0.333,0.333],"y":[0,0,0]},"t":19,"s":[100,106,100],"e":[98.5,105.186,100]},{"i":{"x":[0.667,0.667,0.667],"y":[1,1,1]},"o":{"x":[0.333,0.333,0.333],"y":[0,0.095,0]},"t":20,"s":[98.5,105.186,100],"e":[100,4.455,100]},{"t":38}],"ix":6}},"ao":0,"shapes":[{"ty":"gr","it":[{"ty":"rc","d":1,"s":{"a":0,"k":[54.516,98.049],"ix":2},"p":{"a":0,"k":[0,0],"ix":3},"r":{"a":0,"k":5,"ix":4},"nm":"Rectangle Path 1","mn":"ADBE Vector Shape - Rect","hd":false},{"ty":"gf","o":{"a":0,"k":100,"ix":10},"r":1,"bm":0,"g":{"p":3,"k":{"a":0,"k":[0,0.098,0.149,0.278,0.503,0.098,0.149,0.278,1,0.098,0.149,0.278,0,0.5,0.5,0.25,1,0],"ix":9}},"s":{"a":0,"k":[-26,-49],"ix":5},"e":{"a":0,"k":[29,50],"ix":6},"t":1,"nm":"Gradient Fill 1","mn":"ADBE Vector Graphic - G-Fill","hd":false},{"ty":"tr","p":{"a":0,"k":[0.258,-8.976],"ix":2},"a":{"a":0,"k":[0,0],"ix":1},"s":{"a":0,"k":[100,98.722],"ix":3},"r":{"a":0,"k":0,"ix":6},"o":{"a":0,"k":100,"ix":7},"sk":{"a":0,"k":0,"ix":4},"sa":{"a":0,"k":0,"ix":5},"nm":"Transform"}],"nm":"Rectangle 1","np":3,"cix":2,"bm":0,"ix":1,"mn":"ADBE Vector Group","hd":false}],"ip":0,"op":39,"st":-98,"bm":0}],"markers":[]}